odoo/addons/companyweb_base/README.rst
odoo/addons/companyweb_base/__init__.py
odoo/addons/companyweb_base/__manifest__.py
odoo/addons/companyweb_base/i18n/companyweb_base.pot
odoo/addons/companyweb_base/i18n/fr.po
odoo/addons/companyweb_base/i18n/nl.po
odoo/addons/companyweb_base/models/__init__.py
odoo/addons/companyweb_base/models/res_partner.py
odoo/addons/companyweb_base/models/res_users.py
odoo/addons/companyweb_base/readme/CONTRIBUTORS.rst
odoo/addons/companyweb_base/readme/CREDITS.rst
odoo/addons/companyweb_base/readme/DESCRIPTION.rst
odoo/addons/companyweb_base/readme/INSTALL.rst
odoo/addons/companyweb_base/readme/USAGE.rst
odoo/addons/companyweb_base/security/security.xml
odoo/addons/companyweb_base/static/description/doc_companyweb_data.png
odoo/addons/companyweb_base/static/description/doc_get_credentials.png
odoo/addons/companyweb_base/static/description/doc_install_module.png
odoo/addons/companyweb_base/static/description/doc_on_new_partner.png
odoo/addons/companyweb_base/static/description/doc_security_groups.png
odoo/addons/companyweb_base/static/description/doc_success_message.png
odoo/addons/companyweb_base/static/description/icon.png
odoo/addons/companyweb_base/static/description/index.html
odoo/addons/companyweb_base/static/img/logo-en.png
odoo/addons/companyweb_base/static/img/logo-en.resized.png
odoo/addons/companyweb_base/static/img/cweb_barometer/blanco.png
odoo/addons/companyweb_base/static/img/cweb_barometer/failliet.png
odoo/addons/companyweb_base/static/img/cweb_barometer/neg-01.png
odoo/addons/companyweb_base/static/img/cweb_barometer/neg-02.png
odoo/addons/companyweb_base/static/img/cweb_barometer/neg-03.png
odoo/addons/companyweb_base/static/img/cweb_barometer/neg-04.png
odoo/addons/companyweb_base/static/img/cweb_barometer/neg-05.png
odoo/addons/companyweb_base/static/img/cweb_barometer/neg-06.png
odoo/addons/companyweb_base/static/img/cweb_barometer/neg-07.png
odoo/addons/companyweb_base/static/img/cweb_barometer/neg-08.png
odoo12_addon_companyweb_base-12.0.1.1.2.dist-info/METADATA
odoo12_addon_companyweb_base-12.0.1.1.2.dist-info/WHEEL
odoo12_addon_companyweb_base-12.0.1.1.2.dist-info/top_level.txt
odoo12_addon_companyweb_base-12.0.1.1.2.dist-info/RECORD
